spi_master.v
module spi_master(
    input clk,
    input rst,
    input start,
    input [7:0] data_in,

    output reg mosi,
    output reg sclk,
    output reg ss,
    output reg done
);

reg [7:0] shift_reg;
reg [2:0] bit_count;
reg [1:0] state;

parameter IDLE     = 2'b00;
parameter LOAD     = 2'b01;
parameter TRANSFER = 2'b10;
parameter DONE_ST  = 2'b11;

always @(posedge clk or posedge rst)
begin
    if(rst)
    begin
        state <= IDLE;
        mosi <= 0;
        sclk <= 0;
        ss <= 1;
        done <= 0;
        bit_count <= 0;
    end
    else
    begin
        case(state)

        IDLE:
        begin
            ss <= 1;
            done <= 0;

            if(start)
                state <= LOAD;
        end

        LOAD:
        begin
            shift_reg <= data_in;
            bit_count <= 0;
            ss <= 0;
            state <= TRANSFER;
        end

        TRANSFER:
        begin
            sclk <= ~sclk;

            if(sclk == 0)
            begin
                mosi <= shift_reg[7];
                shift_reg <= {shift_reg[6:0],1'b0};

                if(bit_count == 7)
                    state <= DONE_ST;
                else
                    bit_count <= bit_count + 1;
            end
        end

        DONE_ST:
        begin
            ss <= 1;
            done <= 1;
            state <= IDLE;
        end

        endcase
    end
end

endmodule

tb_spi_master.v
module tb_spi_master;

reg clk;
reg rst;
reg start;
reg [7:0] data_in;

wire mosi;
wire sclk;
wire ss;
wire done;

spi_master uut(
    .clk(clk),
    .rst(rst),
    .start(start),
    .data_in(data_in),
    .mosi(mosi),
    .sclk(sclk),
    .ss(ss),
    .done(done)
);

always #5 clk = ~clk;

initial
begin
    clk = 0;
    rst = 1;
    start = 0;
    data_in = 8'b10110011;

    #10 rst = 0;

    #10 start = 1;
    #10 start = 0;

    #250;

    $finish;
end

initial
begin
    $dumpfile("spi_master.vcd");
    $dumpvars(0,tb_spi_master);
end

endmodule

spi_master.vcd
$date
	Wed Jun 10 18:06:15 2026
$end
$version
	Icarus Verilog
$end
$timescale
	1s
$end
$scope module tb_spi_master $end
$var wire 1 ! ss $end
$var wire 1 " sclk $end
$var wire 1 # mosi $end
$var wire 1 $ done $end
$var reg 1 % clk $end
$var reg 8 & data_in [7:0] $end
$var reg 1 ' rst $end
$var reg 1 ( start $end
$scope module uut $end
$var wire 1 % clk $end
$var wire 8 ) data_in [7:0] $end
$var wire 1 ' rst $end
$var wire 1 ( start $end
$var reg 3 * bit_count [2:0] $end
$var reg 1 $ done $end
$var reg 1 # mosi $end
$var reg 1 " sclk $end
$var reg 8 + shift_reg [7:0] $end
$var reg 1 ! ss $end
$var reg 2 , state [1:0] $end
$upscope $end
$upscope $end
$enddefinitions $end
#0
$dumpvars
b0 ,
bx +
b0 *
b10110011 )
0(
1'
b10110011 &
0%
0$
0#
0"
1!
$end
#5
1%
#10
0%
0'
#15
1%
#20
0%
1(
#25
b1 ,
1%
#30
0%
0(
#35
b10 ,
0!
b10110011 +
1%
#40
0%
#45
b1 *
b1100110 +
1#
1"
1%
#50
0%
#55
0"
1%
#60
0%
#65
b10 *
b11001100 +
0#
1"
1%
#70
0%
#75
0"
1%
#80
0%
#85
b11 *
b10011000 +
1#
1"
1%
#90
0%
#95
0"
1%
#100
0%
#105
b100 *
b110000 +
1"
1%
#110
0%
#115
0"
1%
#120
0%
#125
b101 *
b1100000 +
0#
1"
1%
#130
0%
#135
0"
1%
#140
0%
#145
b110 *
b11000000 +
1"
1%
#150
0%
#155
0"
1%
#160
0%
#165
b111 *
b10000000 +
1#
1"
1%
#170
0%
#175
0"
1%
#180
0%
#185
b11 ,
b0 +
1"
1%
#190
0%
#195
b0 ,
1$
1!
1%
#200
0%
#205
0$
1%
